galaxy_environment/__init__.py
galaxy_environment/distances.py
galaxy_environment/environment.py
galaxy_environment-1.0.1.dist-info/LICENSE
galaxy_environment-1.0.1.dist-info/METADATA
galaxy_environment-1.0.1.dist-info/WHEEL
galaxy_environment-1.0.1.dist-info/top_level.txt
galaxy_environment-1.0.1.dist-info/RECORD
