Metadata-Version: 2.1
Name: galaxy-environment
Version: 1.0.1
Summary: Measuring Galaxies Environments
Home-page: https://github.com/kaykeigh/galaxy-environment
Author: Kayleigh Meneghini
Author-email: kayleighmeneghini@gmail.com
License: Apache License 2.0
Platform: UNKNOWN
Classifier: Programming Language :: Python :: 3
Classifier: Operating System :: OS Independent
Requires-Python: >=3.5
License-File: LICENSE
Requires-Dist: numpy
Requires-Dist: pandas
